optionresult/__init__.py
optionresult/exceptions.py
optionresult/option.py
optionresult/result.py
optionresult-0.1.5.dist-info/METADATA
optionresult-0.1.5.dist-info/WHEEL
optionresult-0.1.5.dist-info/RECORD
